cryptopay/__init__.py
cryptopay/__meta__.py
cryptopay/client/__init__.py
cryptopay/client/api_server.py
cryptopay/client/client.py
cryptopay/client/client.pyi
cryptopay/client/session/__init__.py
cryptopay/client/session/aiohttp.py
cryptopay/client/session/base.py
cryptopay/enums/__init__.py
cryptopay/enums/asset.py
cryptopay/enums/check_status.py
cryptopay/enums/currency_type.py
cryptopay/enums/fiat.py
cryptopay/enums/invoice_status.py
cryptopay/enums/paid_btn_name.py
cryptopay/enums/update_type.py
cryptopay/exceptions.py
cryptopay/loggers.py
cryptopay/methods/__init__.py
cryptopay/methods/base.py
cryptopay/methods/create_check.py
cryptopay/methods/create_invoice.py
cryptopay/methods/delete_check.py
cryptopay/methods/delete_invoice.py
cryptopay/methods/get_balance.py
cryptopay/methods/get_checks.py
cryptopay/methods/get_currencies.py
cryptopay/methods/get_exchange_rates.py
cryptopay/methods/get_invoices.py
cryptopay/methods/get_me.py
cryptopay/methods/get_stats.py
cryptopay/methods/get_transfers.py
cryptopay/methods/transfer.py
cryptopay/polling/__init__.py
cryptopay/polling/manager.py
cryptopay/py.typed
cryptopay/tools/__init__.py
cryptopay/tools/delete_all_checks.py
cryptopay/tools/delete_all_invoices.py
cryptopay/tools/exchange.py
cryptopay/tools/get_balance_by_asset.py
cryptopay/types/__init__.py
cryptopay/types/app.py
cryptopay/types/app_stats.py
cryptopay/types/balance.py
cryptopay/types/base.py
cryptopay/types/base.pyi
cryptopay/types/check.py
cryptopay/types/check.pyi
cryptopay/types/currency.py
cryptopay/types/exchange_rate.py
cryptopay/types/invoice.py
cryptopay/types/invoice.pyi
cryptopay/types/transfer.py
cryptopay/types/update.py
cryptopay/utils/__init__.py
cryptopay/utils/list_serializer.py
cryptopay/utils/propagating_thread.py
cryptopay/utils/sync.py
cryptopay/webhook/__init__.py
cryptopay/webhook/aiohttp_manager.py
cryptopay/webhook/base.py
cryptopay/webhook/fastapi_manager.py
cryptopay/webhook/flask_manager.py
aiocpa-0.1.14.dist-info/LICENSE.txt
aiocpa-0.1.14.dist-info/METADATA
aiocpa-0.1.14.dist-info/WHEEL
aiocpa-0.1.14.dist-info/RECORD
