Metadata-Version: 2.1
Name: aiocpa
Version: 0.1.14
Summary: sync & async Crypto Pay API client.
Home-page: https://github.com/vovchic17/aiocpa
License: MIT
Keywords: crypto pay,CryptoBot,Crypto Pay API
Author: VoVcHiC
Author-email: tsvetkovvova17@gmail.com
Requires-Python: >=3.10,<4.0
Classifier: License :: OSI Approved :: MIT License
Classifier: Programming Language :: Python :: 3
Classifier: Programming Language :: Python :: 3.10
Classifier: Programming Language :: Python :: 3.11
Classifier: Programming Language :: Python :: 3.12
Classifier: Programming Language :: Python :: 3.13
Provides-Extra: docs
Provides-Extra: fastapi
Provides-Extra: flask
Requires-Dist: aiohttp (>=3.9,<4.0)
Requires-Dist: certifi (>=2024.8.30,<2025.0.0)
Requires-Dist: fastapi[standard] (>=0.115.0,<0.116.0) ; extra == "fastapi"
Requires-Dist: flask[async] (>=3.0.3,<4.0.0) ; extra == "flask"
Requires-Dist: furo (>=2024.0.0,<2025.0.0) ; extra == "docs"
Requires-Dist: matplotlib (>=3.9.2,<4.0.0) ; extra == "docs"
Requires-Dist: pydantic (>=2.4,<3.0)
Requires-Dist: sphinx-autodoc-typehints (>=2.3.0,<3.0.0) ; extra == "docs"
Requires-Dist: sphinx-copybutton (>=0.5.2,<0.6.0) ; extra == "docs"
Requires-Dist: sphinxext-opengraph (>=0.9.1,<0.10.0) ; extra == "docs"
Project-URL: Documentation, https://aiocpa.readthedocs.io/en/latest/
Project-URL: Repository, https://github.com/vovchic17/aiocpa
